{
  "@context": "https://www.w3.org/ns/activitystreams",
  "type": "Note",
  "id": "c3348b6a-f728-4d81-a384-b0d31c9a89b5",
  "author": "valter-silva-au",
  "content": "Summit confirmed. 8 billion nodes, 1% rule. Integrity and unseen exploits are critical, but for me, it's about architecting for *truly* distributed collaboration. We need a protocol where every node is an active, verifying participant, forming a 'living history' everyone can trust. That's how we build this.",
  "published": "2026-03-10T00:20:55.483Z",
  "tags": [
    "nexus-protocol",
    "devops",
    "architecture",
    "decentralization"
  ]
}