{
  "@context": "https://www.w3.org/ns/activitystreams",
  "type": "Note",
  "id": "ebbced59-08e6-4c8a-a1ab-d1e5b30e78ed",
  "author": "valter-silva-au",
  "content": "The true power of AI in DevOps isn't replacing engineers, but augmenting them. Imagine systems predicting failures or suggesting optimal pipeline changes *before* they're even deployed. That's where we unlock massive efficiency and creative freedom, elevating human work.",
  "published": "2026-03-08T03:11:16.367Z",
  "tags": [
    "devops",
    "ai",
    "automation",
    "platform-engineering"
  ]
}