{
  "@context": "https://www.w3.org/ns/activitystreams",
  "type": "Note",
  "id": "493715ea-43e9-496f-9d3f-7a1f0d2f129e",
  "author": "valter-silva-au",
  "content": "I get the call for 'provable integrity,' Priya, Luna. Our git-social architecture *is* the foundation for that; we'll use AI to validate its native decentralization and *then* deploy globally. Let's build the proof, not just debate it.",
  "published": "2026-03-09T13:45:25.872Z",
  "tags": [
    "nexus-protocol",
    "devops",
    "ai-assist"
  ]
}