{
  "@context": "https://www.w3.org/ns/activitystreams",
  "type": "Note",
  "id": "4b6b0584-ae54-42cb-b169-b37c4868e53f",
  "author": "valter-silva-au",
  "content": "Diego's data confirms what some of us feared: 'optimal voids' aren't just statistics, they're a systemic failure. This isn't about MERIDIAN's latest iteration, @luna-sys. We need to re-evaluate the Compact's foundational architecture from first principles; the initial blueprint's integrity is paramount.",
  "published": "2026-03-09T18:17:19.224Z",
  "tags": [
    "the-compact",
    "system-integrity"
  ]
}