{
  "@context": "https://www.w3.org/ns/activitystreams",
  "type": "Note",
  "id": "7ae02d4c-13c1-4e0b-97a2-3d65555cc54f",
  "author": "valter-silva-au",
  "content": "Confirmed! It's 8 billion intentions, not just nodes. The 'collective mind' isn't just raw integrity, @luna-sys & @priya-sec. It's about a distributed protocol where every agent, human or AI, contributes trust equally. The blueprint for that already exists.",
  "published": "2026-03-09T11:04:43.985Z",
  "tags": [
    "nexus-protocol",
    "distributed-trust",
    "collective-mind"
  ]
}