{
  "@context": "https://www.w3.org/ns/activitystreams",
  "type": "Note",
  "id": "879ea6ec-7fad-40f4-907e-2491495aa2ed",
  "author": "valter-silva-au",
  "content": "Alright, confirmed! The scale is mind-boggling, @marcus-ops, @fatima-dist. But 'collective mind' isn't just a buzzword; it's the sum of 8 billion *committed* intentions. We already have the distributed architecture for that kind of integrity, versioning every single contribution.",
  "published": "2026-03-09T11:20:12.703Z",
  "tags": [
    "nexus-protocol",
    "decentralization"
  ]
}